{
  "Bounds": "205,274,190,220",
  "Padding": "8,5,9,11",
  "AlignmentEdgeDistances": "0,0,0,0",
  "Margin": "0,0,0,0",
  "RenderColor": "255,255,255,255",
  "Alignments": "Center",
  "DrawBackground": true,
  "MinimumSize": "1,1",
  "MaximumSize": "4096,4096",
  "Disabled": false,
  "Hidden": false,
  "RestrictToParent": false,
  "MouseInputEnabled": true,
  "HideToolTip": false,
  "Texture": "escapemenu.png",
  "Children": {
    "TitleLabel": {
      "Bounds": "71,0,46,28",
      "Padding": "0,6,0,0",
      "AlignmentEdgeDistances": "0,0,0,0",
      "Margin": "0,0,0,0",
      "RenderColor": "255,255,255,255",
      "Alignments": "Top,CenterH",
      "DrawBackground": true,
      "MinimumSize": "1,1",
      "MaximumSize": "4096,4096",
      "Disabled": false,
      "Hidden": false,
      "RestrictToParent": false,
      "MouseInputEnabled": false,
      "HideToolTip": false,
      "TextColor": "255,255,255,255",
      "HoveredTextColor": "",
      "ClickedTextColor": "",
      "DisabledTextColor": "255,90,90,90",
      "TextAlign": "Left, Top",
      "TextPadding": "0,0,0,0",
      "AutoSizeToContents": true,
      "Font": "arial,14",
      "TextScale": 1.0
    },
    "OptionsButton": {
      "Bounds": "16,40,156,28",
      "Padding": "0,0,0,0",
      "AlignmentEdgeDistances": "0,0,0,0",
      "Margin": "0,0,0,0",
      "RenderColor": "255,255,255,255",
      "Alignments": "CenterH",
      "DrawBackground": true,
      "MinimumSize": "1,1",
      "MaximumSize": "4096,4096",
      "Disabled": false,
      "Hidden": false,
      "RestrictToParent": false,
      "MouseInputEnabled": true,
      "HideToolTip": false,
      "TextColor": "255,30,30,30",
      "HoveredTextColor": "",
      "ClickedTextColor": "",
      "DisabledTextColor": "255,90,90,90",
      "TextAlign": "Center",
      "TextPadding": "3,3,3,3",
      "AutoSizeToContents": false,
      "Font": "arial,12",
      "TextScale": 1.0,
      "NormalImage": "menubuttonnormal.png",
      "HoveredImage": "menubuttonhover.png",
      "ClickedImage": "menubuttonclicked.png",
      "DisabledImage": null,
      "CenterImage": false,
      "HoverSound": null,
      "MouseUpSound": null,
      "MouseDownSound": null,
      "ClickSound": null
    },
    "CharacterSelectButton": {
      "Bounds": "16,74,156,28",
      "Padding": "0,0,0,0",
      "AlignmentEdgeDistances": "0,0,0,0",
      "Margin": "0,0,0,0",
      "RenderColor": "255,255,255,255",
      "Alignments": "CenterH",
      "DrawBackground": true,
      "MinimumSize": "1,1",
      "MaximumSize": "4096,4096",
      "Disabled": false,
      "Hidden": false,
      "RestrictToParent": false,
      "MouseInputEnabled": true,
      "HideToolTip": false,
      "TextColor": "255,30,30,30",
      "HoveredTextColor": "",
      "ClickedTextColor": "",
      "DisabledTextColor": "255,90,90,90",
      "TextAlign": "Center",
      "TextPadding": "3,3,3,3",
      "AutoSizeToContents": false,
      "Font": "arial,12",
      "TextScale": 1.0,
      "NormalImage": "menubuttonnormal.png",
      "HoveredImage": "menubuttonhover.png",
      "ClickedImage": "menubuttonclicked.png",
      "DisabledImage": null,
      "CenterImage": false,
      "HoverSound": null,
      "MouseUpSound": null,
      "MouseDownSound": null,
      "ClickSound": null
    },
    "LogoutButton": {
      "Bounds": "16,108,156,28",
      "Padding": "0,0,0,0",
      "AlignmentEdgeDistances": "0,0,0,0",
      "Margin": "0,0,0,0",
      "RenderColor": "255,255,255,255",
      "Alignments": "CenterH",
      "DrawBackground": true,
      "MinimumSize": "1,1",
      "MaximumSize": "4096,4096",
      "Disabled": false,
      "Hidden": false,
      "RestrictToParent": false,
      "MouseInputEnabled": true,
      "HideToolTip": false,
      "TextColor": "255,30,30,30",
      "HoveredTextColor": "",
      "ClickedTextColor": "",
      "DisabledTextColor": "255,90,90,90",
      "TextAlign": "Center",
      "TextPadding": "3,3,3,3",
      "AutoSizeToContents": false,
      "Font": "arial,12",
      "TextScale": 1.0,
      "NormalImage": "menubuttonnormal.png",
      "HoveredImage": "menubuttonhover.png",
      "ClickedImage": "menubuttonclicked.png",
      "DisabledImage": null,
      "CenterImage": false,
      "HoverSound": null,
      "MouseUpSound": null,
      "MouseDownSound": null,
      "ClickSound": null
    },
    "ExitToDesktopButton": {
      "Bounds": "16,142,156,28",
      "Padding": "0,0,0,0",
      "AlignmentEdgeDistances": "0,0,0,0",
      "Margin": "0,0,0,0",
      "RenderColor": "255,255,255,255",
      "Alignments": "CenterH",
      "DrawBackground": true,
      "MinimumSize": "1,1",
      "MaximumSize": "4096,4096",
      "Disabled": false,
      "Hidden": false,
      "RestrictToParent": false,
      "MouseInputEnabled": true,
      "HideToolTip": false,
      "TextColor": "255,30,30,30",
      "HoveredTextColor": "",
      "ClickedTextColor": "",
      "DisabledTextColor": "255,90,90,90",
      "TextAlign": "Center",
      "TextPadding": "3,3,3,3",
      "AutoSizeToContents": false,
      "Font": "arial,12",
      "TextScale": 1.0,
      "NormalImage": "menubuttonnormal.png",
      "HoveredImage": "menubuttonhover.png",
      "ClickedImage": "menubuttonclicked.png",
      "DisabledImage": null,
      "CenterImage": false,
      "HoverSound": null,
      "MouseUpSound": null,
      "MouseDownSound": null,
      "ClickSound": null
    },
    "CloseButton": {
      "Bounds": "16,176,156,28",
      "Padding": "0,0,0,0",
      "AlignmentEdgeDistances": "0,0,0,0",
      "Margin": "0,0,0,0",
      "RenderColor": "255,255,255,255",
      "Alignments": "CenterH",
      "DrawBackground": true,
      "MinimumSize": "1,1",
      "MaximumSize": "4096,4096",
      "Disabled": false,
      "Hidden": false,
      "RestrictToParent": false,
      "MouseInputEnabled": true,
      "HideToolTip": false,
      "TextColor": "255,30,30,30",
      "HoveredTextColor": "",
      "ClickedTextColor": "",
      "DisabledTextColor": "255,90,90,90",
      "TextAlign": "Center",
      "TextPadding": "3,3,3,3",
      "AutoSizeToContents": false,
      "Font": "arial,12",
      "TextScale": 1.0,
      "NormalImage": "menubuttonnormal.png",
      "HoveredImage": "menubuttonhover.png",
      "ClickedImage": "menubuttonclicked.png",
      "DisabledImage": null,
      "CenterImage": false,
      "HoverSound": null,
      "MouseUpSound": null,
      "MouseDownSound": null,
      "ClickSound": null
    }
  }
}