{
  "Bounds": "1129,347,228,320",
  "Padding": "8,5,9,11",
  "AlignmentEdgeDistances": "0,0,0,90",
  "Margin": "0,0,0,0",
  "RenderColor": "255,255,255,255",
  "Alignments": "Bottom,Right",
  "DrawBackground": true,
  "MinimumSize": "100,40",
  "MaximumSize": "4096,4096",
  "Disabled": false,
  "Hidden": true,
  "RestrictToParent": true,
  "MouseInputEnabled": true,
  "HideToolTip": false,
  "ClampMovement": true,
  "ActiveImage": "spellsactive.png",
  "InactiveImage": "",
  "ActiveColor": "255,220,220,220",
  "InactiveColor": "",
  "Closable": true,
  "Titlebar": {
    "Bounds": "0,0,211,24",
    "Padding": "0,0,0,0",
    "AlignmentEdgeDistances": "0,0,0,0",
    "Margin": "0,0,0,0",
    "RenderColor": "255,255,255,255",
    "Alignments": "",
    "DrawBackground": true,
    "MinimumSize": "1,1",
    "MaximumSize": "4096,4096",
    "Disabled": false,
    "Hidden": false,
    "RestrictToParent": false,
    "MouseInputEnabled": true,
    "HideToolTip": false,
    "NormalImage": "",
    "HoveredImage": "",
    "ClickedImage": "",
    "DisabledImage": ""
  },
  "Title": {
    "Bounds": "0,0,53,22",
    "Padding": "0,0,0,0",
    "AlignmentEdgeDistances": "0,0,0,0",
    "Margin": "0,0,0,0",
    "RenderColor": "255,255,255,255",
    "Alignments": "",
    "DrawBackground": true,
    "MinimumSize": "1,1",
    "MaximumSize": "4096,4096",
    "Disabled": false,
    "Hidden": false,
    "RestrictToParent": false,
    "MouseInputEnabled": false,
    "HideToolTip": false,
    "TextColor": "0,255,255,255",
    "HoveredTextColor": "",
    "ClickedTextColor": "",
    "DisabledTextColor": "255,90,90,90",
    "TextAlign": "Left, CenterV",
    "TextPadding": "0,0,0,0",
    "AutoSizeToContents": true,
    "Font": "arial,14",
    "TextScale": 1.0
  },
  "CloseButton": {
    "Bounds": "191,1,20,20",
    "Padding": "3,3,0,3",
    "AlignmentEdgeDistances": "0,0,0,0",
    "Margin": "0,0,0,0",
    "RenderColor": "255,255,255,255",
    "Alignments": "Top,Right",
    "DrawBackground": true,
    "MinimumSize": "1,1",
    "MaximumSize": "20,20",
    "Disabled": false,
    "Hidden": false,
    "RestrictToParent": true,
    "MouseInputEnabled": true,
    "HideToolTip": false,
    "TextColor": "0,255,255,255",
    "HoveredTextColor": "",
    "ClickedTextColor": "",
    "DisabledTextColor": "255,90,90,90",
    "TextAlign": "Center",
    "TextPadding": "3,3,3,3",
    "AutoSizeToContents": false,
    "Font": "arial,10",
    "TextScale": 1.0,
    "NormalImage": "closenormal.png",
    "HoveredImage": "closehover.png",
    "ClickedImage": "closeclicked.png",
    "DisabledImage": "",
    "CenterImage": false,
    "HoverSound": null,
    "MouseUpSound": null,
    "MouseDownSound": null,
    "ClickSound": null
  },
  "InnerPanel": {
    "Bounds": "0,0,10,10",
    "Padding": "0,0,0,0",
    "AlignmentEdgeDistances": "0,0,0,0",
    "Margin": "0,0,0,0",
    "RenderColor": "255,255,255,255",
    "Alignments": "",
    "DrawBackground": true,
    "MinimumSize": "1,1",
    "MaximumSize": "4096,4096",
    "Disabled": false,
    "Hidden": false,
    "RestrictToParent": false,
    "MouseInputEnabled": true,
    "HideToolTip": false,
    "Children": {
      "SpellsContainer": {
        "Bounds": "0,0,211,280",
        "Padding": "0,0,0,0",
        "AlignmentEdgeDistances": "0,0,0,0",
        "Margin": "0,0,0,0",
        "RenderColor": "255,255,255,255",
        "Alignments": "",
        "DrawBackground": true,
        "MinimumSize": "1,1",
        "MaximumSize": "4096,4096",
        "Disabled": false,
        "Hidden": false,
        "RestrictToParent": false,
        "MouseInputEnabled": false,
        "HideToolTip": false,
        "CanScrollH": false,
        "CanScrollV": true,
        "AutoHideBars": false,
        "InnerPanel": {
          "Bounds": "0,0,10,10",
          "Padding": "0,0,0,0",
          "AlignmentEdgeDistances": "0,0,0,0",
          "Margin": "5,5,5,5",
          "RenderColor": "255,255,255,255",
          "Alignments": "",
          "DrawBackground": true,
          "MinimumSize": "1,1",
          "MaximumSize": "4096,4096",
          "Disabled": false,
          "Hidden": false,
          "RestrictToParent": false,
          "MouseInputEnabled": false,
          "HideToolTip": false
        },
        "HorizontalScrollBar": {
          "Bounds": "0,0,15,15",
          "Padding": "0,0,0,0",
          "AlignmentEdgeDistances": "0,0,0,0",
          "Margin": "0,0,0,0",
          "RenderColor": "255,255,255,255",
          "Alignments": "",
          "DrawBackground": true,
          "MinimumSize": "1,1",
          "MaximumSize": "4096,4096",
          "Disabled": false,
          "Hidden": true,
          "RestrictToParent": false,
          "MouseInputEnabled": true,
          "HideToolTip": false,
          "UpOrLeftButton": {
            "Bounds": "0,0,100,20",
            "Padding": "3,3,3,3",
            "AlignmentEdgeDistances": "0,0,0,0",
            "Margin": "0,0,0,0",
            "RenderColor": "255,255,255,255",
            "Alignments": "",
            "DrawBackground": true,
            "MinimumSize": "1,1",
            "MaximumSize": "4096,4096",
            "Disabled": false,
            "Hidden": false,
            "RestrictToParent": false,
            "MouseInputEnabled": true,
            "HideToolTip": false,
            "TextColor": "0,255,255,255",
            "HoveredTextColor": "",
            "ClickedTextColor": "",
            "DisabledTextColor": "255,90,90,90",
            "TextAlign": "Center",
            "TextPadding": "3,3,3,3",
            "AutoSizeToContents": false,
            "Font": "arial,10",
            "TextScale": 1.0,
            "NormalImage": "",
            "HoveredImage": "",
            "ClickedImage": "",
            "DisabledImage": "",
            "CenterImage": false,
            "HoverSound": null,
            "MouseUpSound": null,
            "MouseDownSound": null,
            "ClickSound": null
          },
          "Bar": {
            "Bounds": "0,0,10,10",
            "Padding": "0,0,0,0",
            "AlignmentEdgeDistances": "0,0,0,0",
            "Margin": "0,0,0,0",
            "RenderColor": "255,255,255,255",
            "Alignments": "",
            "DrawBackground": true,
            "MinimumSize": "1,1",
            "MaximumSize": "4096,4096",
            "Disabled": false,
            "Hidden": false,
            "RestrictToParent": true,
            "MouseInputEnabled": true,
            "HideToolTip": false,
            "NormalImage": "",
            "HoveredImage": "",
            "ClickedImage": "",
            "DisabledImage": ""
          },
          "DownOrRightButton": {
            "Bounds": "0,0,100,20",
            "Padding": "3,3,3,3",
            "AlignmentEdgeDistances": "0,0,0,0",
            "Margin": "0,0,0,0",
            "RenderColor": "255,255,255,255",
            "Alignments": "",
            "DrawBackground": true,
            "MinimumSize": "1,1",
            "MaximumSize": "4096,4096",
            "Disabled": false,
            "Hidden": false,
            "RestrictToParent": false,
            "MouseInputEnabled": true,
            "HideToolTip": false,
            "TextColor": "0,255,255,255",
            "HoveredTextColor": "",
            "ClickedTextColor": "",
            "DisabledTextColor": "255,90,90,90",
            "TextAlign": "Center",
            "TextPadding": "3,3,3,3",
            "AutoSizeToContents": false,
            "Font": "arial,10",
            "TextScale": 1.0,
            "NormalImage": "",
            "HoveredImage": "",
            "ClickedImage": "",
            "DisabledImage": "",
            "CenterImage": false,
            "HoverSound": null,
            "MouseUpSound": null,
            "MouseDownSound": null,
            "ClickSound": null
          }
        },
        "VerticalScrollBar": {
          "Bounds": "0,0,15,15",
          "Padding": "0,0,0,0",
          "AlignmentEdgeDistances": "0,0,0,0",
          "Margin": "0,0,0,0",
          "RenderColor": "200,40,40,40",
          "Alignments": "",
          "DrawBackground": true,
          "MinimumSize": "1,1",
          "MaximumSize": "4096,4096",
          "Disabled": false,
          "Hidden": false,
          "RestrictToParent": false,
          "MouseInputEnabled": true,
          "HideToolTip": false,
          "UpOrLeftButton": {
            "Bounds": "0,0,100,20",
            "Padding": "3,3,3,3",
            "AlignmentEdgeDistances": "0,0,0,0",
            "Margin": "0,0,0,0",
            "RenderColor": "255,255,255,255",
            "Alignments": "",
            "DrawBackground": true,
            "MinimumSize": "1,1",
            "MaximumSize": "4096,4096",
            "Disabled": false,
            "Hidden": false,
            "RestrictToParent": false,
            "MouseInputEnabled": true,
            "HideToolTip": false,
            "TextColor": "0,255,255,255",
            "HoveredTextColor": "",
            "ClickedTextColor": "",
            "DisabledTextColor": "255,90,90,90",
            "TextAlign": "Center",
            "TextPadding": "3,3,3,3",
            "AutoSizeToContents": false,
            "Font": "arial,10",
            "TextScale": 1.0,
            "NormalImage": "uparrownormal.png",
            "HoveredImage": "uparrowhover.png",
            "ClickedImage": "uparrowclicked.png",
            "DisabledImage": "",
            "CenterImage": false,
            "HoverSound": null,
            "MouseUpSound": null,
            "MouseDownSound": null,
            "ClickSound": null
          },
          "Bar": {
            "Bounds": "0,0,10,10",
            "Padding": "0,0,0,0",
            "AlignmentEdgeDistances": "0,0,0,0",
            "Margin": "0,0,0,0",
            "RenderColor": "255,255,255,255",
            "Alignments": "",
            "DrawBackground": true,
            "MinimumSize": "1,1",
            "MaximumSize": "4096,4096",
            "Disabled": false,
            "Hidden": false,
            "RestrictToParent": true,
            "MouseInputEnabled": true,
            "HideToolTip": false,
            "NormalImage": "scrollbarnormal.png",
            "HoveredImage": "scrollbarhover.png",
            "ClickedImage": "scrollbarclicked.png",
            "DisabledImage": ""
          },
          "DownOrRightButton": {
            "Bounds": "0,0,100,20",
            "Padding": "3,3,3,3",
            "AlignmentEdgeDistances": "0,0,0,0",
            "Margin": "0,0,0,0",
            "RenderColor": "255,255,255,255",
            "Alignments": "",
            "DrawBackground": true,
            "MinimumSize": "1,1",
            "MaximumSize": "4096,4096",
            "Disabled": false,
            "Hidden": false,
            "RestrictToParent": false,
            "MouseInputEnabled": true,
            "HideToolTip": false,
            "TextColor": "0,255,255,255",
            "HoveredTextColor": "",
            "ClickedTextColor": "",
            "DisabledTextColor": "255,90,90,90",
            "TextAlign": "Center",
            "TextPadding": "3,3,3,3",
            "AutoSizeToContents": false,
            "Font": "arial,10",
            "TextScale": 1.0,
            "NormalImage": "downarrownormal.png",
            "HoveredImage": "downarrowhover.png",
            "ClickedImage": "downarrowclicked.png",
            "DisabledImage": "",
            "CenterImage": false,
            "HoverSound": null,
            "MouseUpSound": null,
            "MouseDownSound": null,
            "ClickSound": null
          }
        }
      }
    }
  }
}